package_creation_tutorial/__init__.py
package_creation_tutorial/main.py
package_creation_tutorial/setup.py
package_creation_tutorial/string_ops.py
package_creation_tutorial_borghel-0.1.1.dist-info/LICENCE
package_creation_tutorial_borghel-0.1.1.dist-info/METADATA
package_creation_tutorial_borghel-0.1.1.dist-info/WHEEL
package_creation_tutorial_borghel-0.1.1.dist-info/RECORD
